taxon_parser/__init__.py
taxon_parser/name_parser_api/__init__.py
taxon_parser/name_parser_api/authorship.py
taxon_parser/name_parser_api/namepart.py
taxon_parser/name_parser_api/parsedname.py
taxon_parser/name_parser_api/rank.py
taxon_parser/name_parser_api/util/__init__.py
taxon_parser/name_parser_api/util/nameformatter.py
taxon_parser/name_parser_api/util/nameparts.py
taxon_parser/name_parser_api/util/rankutils.py
taxon_parser/name_parser_api/util/unicodeutils.py
taxon_parser/resources/latin-endings.txt
taxon_parser-0.2.0.dist-info/DESCRIPTION.rst
taxon_parser-0.2.0.dist-info/METADATA
taxon_parser-0.2.0.dist-info/RECORD
taxon_parser-0.2.0.dist-info/WHEEL
taxon_parser-0.2.0.dist-info/metadata.json
taxon_parser-0.2.0.dist-info/top_level.txt
