Metadata-Version: 2.0
Name: taxon-parser
Version: 0.2.0
Summary: A library to parse taxon names into elementary components
Home-page: https://github.com/aroche/taxon_parser
Author: Augustin Roche
Author-email: aroche@photoherbarium.fr
License: UNKNOWN
Platform: UNKNOWN
Classifier: Programming Language :: Python :: 3
Classifier: License :: OSI Approved :: Apache Software License
Classifier: Operating System :: OS Independent
Requires-Python: >=3.4
Requires-Dist: regex
